parkTest/test1.py
parkTest/test2.py
parkTest-0.0.0.2.dist-info/METADATA
parkTest-0.0.0.2.dist-info/WHEEL
parkTest-0.0.0.2.dist-info/top_level.txt
parkTest-0.0.0.2.dist-info/RECORD
