Metadata-Version: 2.1
Name: parkTest
Version: 0.0.0.2
Summary: My First Test Package
Home-page: https://lingua.blog.me/...
Author: Park
Author-email: pdh0184@naver.com
License: MIT
Requires-Python: >=3
